Metadata-Version: 2.4
Name: secrets_sdk
Version: 0.1.0
Summary: In-process Canonical Secret URI client with PEP enforcement and Vault providers
Author: EmpowerNow
Requires-Python: >=3.11
Requires-Dist: hvac>=2.1.0
Requires-Dist: tenacity>=8.2.3
Requires-Dist: cachetools>=5.3.3
Provides-Extra: dev
Requires-Dist: pytest>=8.2.0; extra == "dev"
Requires-Dist: pytest-asyncio>=0.23.8; extra == "dev"
